LMS/__init__.py
libPyMS-0.1.0.dist-info/METADATA
libPyMS-0.1.0.dist-info/WHEEL
libPyMS-0.1.0.dist-info/top_level.txt
libPyMS-0.1.0.dist-info/RECORD
